{
    "Movie": [
        {
            "ranking": 1,
            "title": "Planet Earth II",
            "rating": "9.5"
        },
        {
            "ranking": 2,
            "title": "Band of Brothers",
            "rating": "9.5"
        },
        {
            "ranking": 3,
            "title": "Planet Earth",
            "rating": "9.5"
        },
        {
            "ranking": 4,
            "title": "Game of Thrones",
            "rating": "9.4"
        },
        {
            "ranking": 5,
            "title": "Breaking Bad",
            "rating": "9.4"
        },
        {
            "ranking": 6,
            "title": "The Wire",
            "rating": "9.3"
        },
        {
            "ranking": 7,
            "title": "Rick and Morty",
            "rating": "9.3"
        },
        {
            "ranking": 8,
            "title": "Cosmos: A Spacetime Odyssey",
            "rating": "9.3"
        },
        {
            "ranking": 9,
            "title": "Cosmos",
            "rating": "9.2"
        },
        {
            "ranking": 10,
            "title": "The World at War",
            "rating": "9.2"
        },
        {
            "ranking": 11,
            "title": "The Sopranos",
            "rating": "9.2"
        },
        {
            "ranking": 12,
            "title": "Sherlock",
            "rating": "9.1"
        },
        {
            "ranking": 13,
            "title": "Life",
            "rating": "9.1"
        },
        {
            "ranking": 14,
            "title": "Avatar: The Last Airbender",
            "rating": "9.1"
        },
        {
            "ranking": 15,
            "title": "The Civil War",
            "rating": "9.1"
        },
        {
            "ranking": 16,
            "title": "Human Planet",
            "rating": "9.0"
        },
        {
            "ranking": 17,
            "title": "Firefly",
            "rating": "9.0"
        },
        {
            "ranking": 18,
            "title": "Dekalog",
            "rating": "9.0"
        },
        {
            "ranking": 19,
            "title": "The Twilight Zone",
            "rating": "9.0"
        },
        {
            "ranking": 20,
            "title": "Last Week Tonight with John Oliver",
            "rating": "9.0"
        },
        {
            "ranking": 21,
            "title": "True Detective",
            "rating": "9.0"
        },
        {
            "ranking": 22,
            "title": "Hagane no renkinjutsushi",
            "rating": "9.0"
        },
        {
            "ranking": 23,
            "title": "Fargo",
            "rating": "9.0"
        },
        {
            "ranking": 24,
            "title": "Batman: The Animated Series",
            "rating": "9.0"
        },
        {
            "ranking": 25,
            "title": "The Blue Planet",
            "rating": "8.9"
        },
        {
            "ranking": 26,
            "title": "Death Note: Desu nôto",
            "rating": "8.9"
        },
        {
            "ranking": 27,
            "title": "One Punch Man: Wanpanman",
            "rating": "8.9"
        },
        {
            "ranking": 28,
            "title": "Westworld",
            "rating": "8.9"
        },
        {
            "ranking": 29,
            "title": "Frozen Planet",
            "rating": "8.9"
        },
        {
            "ranking": 30,
            "title": "Cowboy Bebop",
            "rating": "8.9"
        },
        {
            "ranking": 31,
            "title": "House of Cards",
            "rating": "8.9"
        },
        {
            "ranking": 32,
            "title": "Africa",
            "rating": "8.9"
        },
        {
            "ranking": 33,
            "title": "Monty Python's Flying Circus",
            "rating": "8.9"
        },
        {
            "ranking": 34,
            "title": "Pride and Prejudice",
            "rating": "8.9"
        },
        {
            "ranking": 35,
            "title": "Das Boot",
            "rating": "8.9"
        },
        {
            "ranking": 36,
            "title": "TVF Pitchers",
            "rating": "8.9"
        },
        {
            "ranking": 37,
            "title": "Arrested Development",
            "rating": "8.9"
        },
        {
            "ranking": 38,
            "title": "Stranger Things",
            "rating": "8.9"
        },
        {
            "ranking": 39,
            "title": "Black Mirror",
            "rating": "8.9"
        },
        {
            "ranking": 40,
            "title": "Over the Garden Wall",
            "rating": "8.9"
        },
        {
            "ranking": 41,
            "title": "Friends",
            "rating": "8.9"
        },
        {
            "ranking": 42,
            "title": "Seinfeld",
            "rating": "8.9"
        },
        {
            "ranking": 43,
            "title": "Only Fools and Horses....",
            "rating": "8.9"
        },
        {
            "ranking": 44,
            "title": "Sarabhai vs Sarabhai",
            "rating": "8.8"
        },
        {
            "ranking": 45,
            "title": "Twin Peaks",
            "rating": "8.8"
        },
        {
            "ranking": 46,
            "title": "I, Claudius",
            "rating": "8.8"
        },
        {
            "ranking": 47,
            "title": "Narcos",
            "rating": "8.8"
        },
        {
            "ranking": 48,
            "title": "Freaks and Geeks",
            "rating": "8.8"
        },
        {
            "ranking": 49,
            "title": "Gravity Falls",
            "rating": "8.8"
        },
        {
            "ranking": 50,
            "title": "Blackadder Goes Forth",
            "rating": "8.8"
        },
        {
            "ranking": 51,
            "title": "Fawlty Towers",
            "rating": "8.8"
        },
        {
            "ranking": 52,
            "title": "Rome",
            "rating": "8.8"
        },
        {
            "ranking": 53,
            "title": "Oz",
            "rating": "8.8"
        },
        {
            "ranking": 54,
            "title": "The Simpsons",
            "rating": "8.8"
        },
        {
            "ranking": 55,
            "title": "The Return of Sherlock Holmes",
            "rating": "8.7"
        },
        {
            "ranking": 56,
            "title": "South Park",
            "rating": "8.7"
        },
        {
            "ranking": 57,
            "title": "The Jinx: The Life and Deaths of Robert Durst",
            "rating": "8.7"
        },
        {
            "ranking": 58,
            "title": "The Office",
            "rating": "8.7"
        },
        {
            "ranking": 59,
            "title": "Attack on Titan",
            "rating": "8.7"
        },
        {
            "ranking": 60,
            "title": "It's Always Sunny in Philadelphia",
            "rating": "8.7"
        },
        {
            "ranking": 61,
            "title": "The Grand Tour",
            "rating": "8.7"
        },
        {
            "ranking": 62,
            "title": "This Is Us",
            "rating": "8.7"
        },
        {
            "ranking": 63,
            "title": "Dragon Ball Z",
            "rating": "8.7"
        },
        {
            "ranking": 64,
            "title": "House M.D.",
            "rating": "8.7"
        },
        {
            "ranking": 65,
            "title": "Peaky Blinders",
            "rating": "8.7"
        },
        {
            "ranking": 66,
            "title": "Twin Peaks",
            "rating": "8.7"
        },
        {
            "ranking": 67,
            "title": "The Adventures of Sherlock Holmes",
            "rating": "8.7"
        },
        {
            "ranking": 68,
            "title": "Chappelle's Show",
            "rating": "8.7"
        },
        {
            "ranking": 69,
            "title": "The West Wing",
            "rating": "8.7"
        },
        {
            "ranking": 70,
            "title": "Steins;Gate",
            "rating": "8.7"
        },
        {
            "ranking": 71,
            "title": "Six Feet Under",
            "rating": "8.7"
        },
        {
            "ranking": 72,
            "title": "Making a Murderer",
            "rating": "8.7"
        },
        {
            "ranking": 73,
            "title": "Archer",
            "rating": "8.7"
        },
        {
            "ranking": 74,
            "title": "Dragon Ball Z: Doragon bôru zetto",
            "rating": "8.7"
        },
        {
            "ranking": 75,
            "title": "Lonesome Dove",
            "rating": "8.7"
        },
        {
            "ranking": 76,
            "title": "The Crown",
            "rating": "8.7"
        },
        {
            "ranking": 77,
            "title": "From the Earth to the Moon",
            "rating": "8.7"
        },
        {
            "ranking": 78,
            "title": "Top Gear",
            "rating": "8.7"
        },
        {
            "ranking": 79,
            "title": "Deadwood",
            "rating": "8.7"
        },
        {
            "ranking": 80,
            "title": "Long Way Round",
            "rating": "8.7"
        },
        {
            "ranking": 81,
            "title": "Skam",
            "rating": "8.7"
        },
        {
            "ranking": 82,
            "title": "The Thick of It",
            "rating": "8.7"
        },
        {
            "ranking": 83,
            "title": "Better Call Saul",
            "rating": "8.7"
        },
        {
            "ranking": 84,
            "title": "Battlestar Galactica",
            "rating": "8.7"
        },
        {
            "ranking": 85,
            "title": "Dexter",
            "rating": "8.7"
        },
        {
            "ranking": 86,
            "title": "North & South",
            "rating": "8.7"
        },
        {
            "ranking": 87,
            "title": "Daredevil",
            "rating": "8.7"
        },
        {
            "ranking": 88,
            "title": "Curb Your Enthusiasm",
            "rating": "8.7"
        },
        {
            "ranking": 89,
            "title": "Nathan for You",
            "rating": "8.7"
        },
        {
            "ranking": 90,
            "title": "Hunter x Hunter",
            "rating": "8.7"
        },
        {
            "ranking": 91,
            "title": "The X-Files",
            "rating": "8.7"
        },
        {
            "ranking": 92,
            "title": "The Shield",
            "rating": "8.7"
        },
        {
            "ranking": 93,
            "title": "Black-Adder II",
            "rating": "8.7"
        },
        {
            "ranking": 94,
            "title": "Horace and Pete",
            "rating": "8.6"
        },
        {
            "ranking": 95,
            "title": "Berserk",
            "rating": "8.6"
        },
        {
            "ranking": 96,
            "title": "Mystery Science Theater 3000",
            "rating": "8.6"
        },
        {
            "ranking": 97,
            "title": "Doctor Who",
            "rating": "8.6"
        },
        {
            "ranking": 98,
            "title": "Kôdo giasu: Hangyaku no rurûshu",
            "rating": "8.6"
        },
        {
            "ranking": 99,
            "title": "Rurouni Kenshin: Meiji Kenkaku Romantan: Tsuioku Hen",
            "rating": "8.6"
        },
        {
            "ranking": 100,
            "title": "Black Adder the Third",
            "rating": "8.6"
        },
        {
            "ranking": 101,
            "title": "Shameless",
            "rating": "8.6"
        },
        {
            "ranking": 102,
            "title": "QI",
            "rating": "8.6"
        },
        {
            "ranking": 103,
            "title": "Downton Abbey",
            "rating": "8.6"
        },
        {
            "ranking": 104,
            "title": "Spaced",
            "rating": "8.6"
        },
        {
            "ranking": 105,
            "title": "Through the Wormhole",
            "rating": "8.6"
        },
        {
            "ranking": 106,
            "title": "Brass Eye",
            "rating": "8.6"
        },
        {
            "ranking": 107,
            "title": "The Handmaid's Tale",
            "rating": "8.6"
        },
        {
            "ranking": 108,
            "title": "Fullmetal Alchemist",
            "rating": "8.6"
        },
        {
            "ranking": 109,
            "title": "Battlestar Galactica",
            "rating": "8.6"
        },
        {
            "ranking": 110,
            "title": "Young Justice",
            "rating": "8.6"
        },
        {
            "ranking": 111,
            "title": "Star Trek: The Next Generation",
            "rating": "8.6"
        },
        {
            "ranking": 112,
            "title": "The Daily Show",
            "rating": "8.6"
        },
        {
            "ranking": 113,
            "title": "Chef's Table",
            "rating": "8.6"
        },
        {
            "ranking": 114,
            "title": "Yes Minister",
            "rating": "8.6"
        },
        {
            "ranking": 115,
            "title": "Leyla ile Mecnun",
            "rating": "8.6"
        },
        {
            "ranking": 116,
            "title": "Parks and Recreation",
            "rating": "8.6"
        },
        {
            "ranking": 117,
            "title": "Big Little Lies",
            "rating": "8.6"
        },
        {
            "ranking": 118,
            "title": "Yes, Prime Minister",
            "rating": "8.6"
        },
        {
            "ranking": 119,
            "title": "Mad Men",
            "rating": "8.6"
        },
        {
            "ranking": 120,
            "title": "Louie",
            "rating": "8.6"
        },
        {
            "ranking": 121,
            "title": "The Bugs Bunny Show",
            "rating": "8.6"
        },
        {
            "ranking": 122,
            "title": "The Night Of",
            "rating": "8.6"
        },
        {
            "ranking": 123,
            "title": "Friday Night Lights",
            "rating": "8.6"
        },
        {
            "ranking": 124,
            "title": "Generation Kill",
            "rating": "8.6"
        },
        {
            "ranking": 125,
            "title": "Monster",
            "rating": "8.6"
        },
        {
            "ranking": 126,
            "title": "Samurai Champloo",
            "rating": "8.6"
        },
        {
            "ranking": 127,
            "title": "Flight of the Conchords",
            "rating": "8.6"
        },
        {
            "ranking": 128,
            "title": "Gomorra: La serie",
            "rating": "8.6"
        },
        {
            "ranking": 129,
            "title": "Father Ted",
            "rating": "8.6"
        },
        {
            "ranking": 130,
            "title": "Bron/Broen",
            "rating": "8.6"
        },
        {
            "ranking": 131,
            "title": "Adventure Time",
            "rating": "8.6"
        },
        {
            "ranking": 132,
            "title": "Justice League",
            "rating": "8.6"
        },
        {
            "ranking": 133,
            "title": "Impractical Jokers",
            "rating": "8.6"
        },
        {
            "ranking": 134,
            "title": "John Adams",
            "rating": "8.6"
        },
        {
            "ranking": 135,
            "title": "Justified",
            "rating": "8.6"
        },
        {
            "ranking": 136,
            "title": "Shin Seiki Evangerion",
            "rating": "8.6"
        },
        {
            "ranking": 137,
            "title": "Mr. Robot",
            "rating": "8.6"
        },
        {
            "ranking": 138,
            "title": "Dr. Horrible's Sing-Along Blog",
            "rating": "8.6"
        },
        {
            "ranking": 139,
            "title": "Boardwalk Empire",
            "rating": "8.6"
        },
        {
            "ranking": 140,
            "title": "Homicide: Life on the Street",
            "rating": "8.6"
        },
        {
            "ranking": 141,
            "title": "The Newsroom",
            "rating": "8.6"
        },
        {
            "ranking": 142,
            "title": "Alfred Hitchcock Presents",
            "rating": "8.5"
        },
        {
            "ranking": 143,
            "title": "Taboo",
            "rating": "8.5"
        },
        {
            "ranking": 144,
            "title": "Coupling",
            "rating": "8.5"
        },
        {
            "ranking": 145,
            "title": "Peep Show",
            "rating": "8.5"
        },
        {
            "ranking": 146,
            "title": "Feud",
            "rating": "8.5"
        },
        {
            "ranking": 147,
            "title": "Dragon Ball: Doragon bôru",
            "rating": "8.5"
        },
        {
            "ranking": 148,
            "title": "House of Cards",
            "rating": "8.5"
        },
        {
            "ranking": 149,
            "title": "The Office",
            "rating": "8.5"
        },
        {
            "ranking": 150,
            "title": "Kardes Payi",
            "rating": "8.5"
        },
        {
            "ranking": 151,
            "title": "Vikings",
            "rating": "8.5"
        },
        {
            "ranking": 152,
            "title": "Dragon Ball",
            "rating": "8.5"
        },
        {
            "ranking": 153,
            "title": "Agatha Christie's Poirot",
            "rating": "8.5"
        },
        {
            "ranking": 154,
            "title": "Whose Line Is It Anyway?",
            "rating": "8.5"
        },
        {
            "ranking": 155,
            "title": "The New Batman Adventures",
            "rating": "8.5"
        },
        {
            "ranking": 156,
            "title": "The Prisoner",
            "rating": "8.5"
        },
        {
            "ranking": 157,
            "title": "Tinker Tailor Soldier Spy",
            "rating": "8.5"
        },
        {
            "ranking": 158,
            "title": "One Piece: Wan pîsu",
            "rating": "8.5"
        },
        {
            "ranking": 159,
            "title": "Rurouni Kenshin: Wandering Samurai",
            "rating": "8.5"
        },
        {
            "ranking": 160,
            "title": "Spartacus: Gods of the Arena",
            "rating": "8.5"
        },
        {
            "ranking": 161,
            "title": "Ash vs Evil Dead",
            "rating": "8.5"
        },
        {
            "ranking": 162,
            "title": "The IT Crowd",
            "rating": "8.5"
        },
        {
            "ranking": 163,
            "title": "Silicon Valley",
            "rating": "8.5"
        },
        {
            "ranking": 164,
            "title": "Clannad: After Story",
            "rating": "8.5"
        },
        {
            "ranking": 165,
            "title": "The Colbert Report",
            "rating": "8.5"
        },
        {
            "ranking": 166,
            "title": "American Crime Story",
            "rating": "8.5"
        },
        {
            "ranking": 167,
            "title": "Kôkaku kidôtai: Stand Alone Complex",
            "rating": "8.5"
        },
        {
            "ranking": 168,
            "title": "Luther",
            "rating": "8.5"
        },
        {
            "ranking": 169,
            "title": "Mr. Bean",
            "rating": "8.5"
        },
        {
            "ranking": 170,
            "title": "Ozark",
            "rating": "8.5"
        },
        {
            "ranking": 171,
            "title": "The Venture Bros.",
            "rating": "8.5"
        },
        {
            "ranking": 172,
            "title": "Atlanta",
            "rating": "8.5"
        },
        {
            "ranking": 173,
            "title": "Black Books",
            "rating": "8.5"
        },
        {
            "ranking": 174,
            "title": "The Angry Video Game Nerd",
            "rating": "8.5"
        },
        {
            "ranking": 175,
            "title": "The Legend of Korra",
            "rating": "8.5"
        },
        {
            "ranking": 176,
            "title": "Suits",
            "rating": "8.5"
        },
        {
            "ranking": 177,
            "title": "Hannibal",
            "rating": "8.5"
        },
        {
            "ranking": 178,
            "title": "I'm Alan Partridge",
            "rating": "8.5"
        },
        {
            "ranking": 179,
            "title": "Behzat Ç.: Bir Ankara Polisiyesi",
            "rating": "8.5"
        },
        {
            "ranking": 180,
            "title": "Futurama",
            "rating": "8.5"
        },
        {
            "ranking": 181,
            "title": "Wentworth",
            "rating": "8.5"
        },
        {
            "ranking": 182,
            "title": "Jesus of Nazareth",
            "rating": "8.5"
        },
        {
            "ranking": 183,
            "title": "Sons of Anarchy",
            "rating": "8.5"
        },
        {
            "ranking": 184,
            "title": "Boku dake ga inai machi",
            "rating": "8.5"
        },
        {
            "ranking": 185,
            "title": "Spartacus: War of the Damned",
            "rating": "8.5"
        },
        {
            "ranking": 186,
            "title": "The Knick",
            "rating": "8.5"
        },
        {
            "ranking": 187,
            "title": "Community",
            "rating": "8.5"
        },
        {
            "ranking": 188,
            "title": "Legion",
            "rating": "8.5"
        },
        {
            "ranking": 189,
            "title": "Garth Marenghi's Darkplace",
            "rating": "8.5"
        },
        {
            "ranking": 190,
            "title": "Endeavour",
            "rating": "8.5"
        },
        {
            "ranking": 191,
            "title": "Police Squad!",
            "rating": "8.5"
        },
        {
            "ranking": 192,
            "title": "Permanent Roommates",
            "rating": "8.5"
        },
        {
            "ranking": 193,
            "title": "Carnivàle",
            "rating": "8.5"
        },
        {
            "ranking": 194,
            "title": "X-Men",
            "rating": "8.5"
        },
        {
            "ranking": 195,
            "title": "Isler Güçler",
            "rating": "8.4"
        },
        {
            "ranking": 196,
            "title": "Scenes from a Marriage",
            "rating": "8.4"
        },
        {
            "ranking": 197,
            "title": "Generation War",
            "rating": "8.4"
        },
        {
            "ranking": 198,
            "title": "Happy Valley",
            "rating": "8.4"
        },
        {
            "ranking": 199,
            "title": "Modern Family",
            "rating": "8.4"
        },
        {
            "ranking": 200,
            "title": "State of Play",
            "rating": "8.4"
        },
        {
            "ranking": 201,
            "title": "Samurai Jack",
            "rating": "8.4"
        },
        {
            "ranking": 202,
            "title": "Entourage",
            "rating": "8.4"
        },
        {
            "ranking": 203,
            "title": "Jeeves and Wooster",
            "rating": "8.4"
        },
        {
            "ranking": 204,
            "title": "Utopia",
            "rating": "8.4"
        },
        {
            "ranking": 205,
            "title": "Mushi-Shi",
            "rating": "8.4"
        },
        {
            "ranking": 206,
            "title": "The Muppet Show",
            "rating": "8.4"
        },
        {
            "ranking": 207,
            "title": "Doctor Who",
            "rating": "8.4"
        },
        {
            "ranking": 208,
            "title": "The Larry Sanders Show",
            "rating": "8.4"
        },
        {
            "ranking": 209,
            "title": "Line of Duty",
            "rating": "8.4"
        },
        {
            "ranking": 210,
            "title": "Parasyte: The Maxim",
            "rating": "8.4"
        },
        {
            "ranking": 211,
            "title": "Yu Yu Hakusho: Ghost Files",
            "rating": "8.4"
        },
        {
            "ranking": 212,
            "title": "Borgen",
            "rating": "8.4"
        },
        {
            "ranking": 213,
            "title": "13 Reasons Why",
            "rating": "8.4"
        },
        {
            "ranking": 214,
            "title": "Roots",
            "rating": "8.4"
        },
        {
            "ranking": 215,
            "title": "Whose Line Is It Anyway?",
            "rating": "8.4"
        },
        {
            "ranking": 216,
            "title": "Anne with an E",
            "rating": "8.4"
        },
        {
            "ranking": 217,
            "title": "Mr. Show with Bob and David",
            "rating": "8.4"
        },
        {
            "ranking": 218,
            "title": "Southland",
            "rating": "8.4"
        },
        {
            "ranking": 219,
            "title": "The Walking Dead",
            "rating": "8.4"
        },
        {
            "ranking": 220,
            "title": "Red Dwarf",
            "rating": "8.4"
        },
        {
            "ranking": 221,
            "title": "Naruto: Shippûden",
            "rating": "8.4"
        },
        {
            "ranking": 222,
            "title": "Riget",
            "rating": "8.4"
        },
        {
            "ranking": 223,
            "title": "Brigada",
            "rating": "8.4"
        },
        {
            "ranking": 224,
            "title": "Summer Heights High",
            "rating": "8.4"
        },
        {
            "ranking": 225,
            "title": "Hellsing Ultimate",
            "rating": "8.4"
        },
        {
            "ranking": 226,
            "title": "My Mad Fat Diary",
            "rating": "8.4"
        },
        {
            "ranking": 227,
            "title": "Trailer Park Boys",
            "rating": "8.4"
        },
        {
            "ranking": 228,
            "title": "Supernatural",
            "rating": "8.4"
        },
        {
            "ranking": 229,
            "title": "24: Live Another Day",
            "rating": "8.4"
        },
        {
            "ranking": 230,
            "title": "Fringe",
            "rating": "8.3"
        },
        {
            "ranking": 231,
            "title": "Top Gear",
            "rating": "8.3"
        },
        {
            "ranking": 232,
            "title": "The Inbetweeners",
            "rating": "8.3"
        },
        {
            "ranking": 233,
            "title": "BoJack Horseman",
            "rating": "8.3"
        },
        {
            "ranking": 234,
            "title": "Lost",
            "rating": "8.3"
        },
        {
            "ranking": 235,
            "title": "Broadchurch",
            "rating": "8.3"
        },
        {
            "ranking": 236,
            "title": "Dragon Ball Z Kai",
            "rating": "8.3"
        },
        {
            "ranking": 237,
            "title": "Billions",
            "rating": "8.3"
        },
        {
            "ranking": 238,
            "title": "Olive Kitteridge",
            "rating": "8.3"
        },
        {
            "ranking": 239,
            "title": "Stargate SG-1",
            "rating": "8.3"
        },
        {
            "ranking": 240,
            "title": "Star Trek",
            "rating": "8.3"
        },
        {
            "ranking": 241,
            "title": "Pushing Daisies",
            "rating": "8.3"
        },
        {
            "ranking": 242,
            "title": "Boston Legal",
            "rating": "8.3"
        },
        {
            "ranking": 243,
            "title": "M*A*S*H",
            "rating": "8.3"
        },
        {
            "ranking": 244,
            "title": "Bleak House",
            "rating": "8.3"
        },
        {
            "ranking": 245,
            "title": "I Love Lucy",
            "rating": "8.3"
        },
        {
            "ranking": 246,
            "title": "Person of Interest",
            "rating": "8.3"
        },
        {
            "ranking": 247,
            "title": "Extras",
            "rating": "8.3"
        },
        {
            "ranking": 248,
            "title": "Broad City",
            "rating": "8.3"
        },
        {
            "ranking": 249,
            "title": "Scrubs",
            "rating": "8.3"
        },
        {
            "ranking": 250,
            "title": "Banshee",
            "rating": "8.3"
        }
    ]
}